fixaudit/__init__.py
fixaudit/fixaudit.py
fixorchestra/__init__.py
fixorchestra/orchestration.py
fixorchestra/test_orchestration.py
fixorchestra-0.0.3.dist-info/licenses/LICENSE
fixrepository/__init__.py
fixrepository/repository.py
fixrepository/test_repository.py
fixreptorc/__init__.py
fixreptorc/fixreptorc.py
fixorchestra-0.0.3.dist-info/METADATA
fixorchestra-0.0.3.dist-info/WHEEL
fixorchestra-0.0.3.dist-info/entry_points.txt
fixorchestra-0.0.3.dist-info/top_level.txt
fixorchestra-0.0.3.dist-info/RECORD
