Metadata-Version: 2.4
Name: fixorchestra
Version: 0.0.3
Summary: Explore, manipulate, compare, and convert fixtrading.org orchestrations and repositories.
Author-email: Gary Hughes <garyedwardhughes@gmail.com>
License: MIT
Project-URL: Homepage, https://github.com/GaryHughes/fixorchestra
Classifier: Programming Language :: Python :: 3
Classifier: Operating System :: OS Independent
Requires-Python: >=3.6
License-File: LICENSE
Provides-Extra: test
Requires-Dist: pytest; extra == "test"
Requires-Dist: pytest-cov; extra == "test"
Dynamic: license-file
